EnzymePynetics/__init__.py
EnzymePynetics/core/__init__.py
EnzymePynetics/core/concentrationtypes.py
EnzymePynetics/core/enzymekineticsexperiment.py
EnzymePynetics/core/measurement.py
EnzymePynetics/core/series.py
EnzymePynetics/core/stoichiometrytypes.py
EnzymePynetics/core/timetypes.py
EnzymePynetics/tools/__init__.py
EnzymePynetics/tools/kineticmodel.py
EnzymePynetics/tools/parameterestimator.py
EnzymePynetics-0.0.2.dist-info/METADATA
EnzymePynetics-0.0.2.dist-info/WHEEL
EnzymePynetics-0.0.2.dist-info/top_level.txt
EnzymePynetics-0.0.2.dist-info/RECORD
