Metadata-Version: 2.1
Name: EnzymePynetics
Version: 0.0.2
Summary: Parameter estimation for enzyme kinetics.
Home-page: https://github.com/haeussma/EnzymePynetics
Author: Haeussler, Max
Author-email: st171427@stud.uni-stuttgart.de
License: UNKNOWN
Platform: UNKNOWN
Requires-Dist: lmfit
Requires-Dist: matplotlib
Requires-Dist: numpy
Requires-Dist: pandas
Requires-Dist: pydantic
Requires-Dist: scipy
Requires-Dist: setuptools
